blmm/__init__.py
blmm/blmm_cluster.py
blmm/lib/__init__.py
blmm/lib/blmm_batch.py
blmm/lib/blmm_cleanup.py
blmm/lib/blmm_compare.py
blmm/lib/blmm_concat.py
blmm/lib/blmm_estimate.py
blmm/lib/blmm_inference.py
blmm/lib/blmm_results.py
blmm/lib/blmm_setup.py
blmm/scripts/cluster_blmm_batch.sh
blmm/scripts/cluster_blmm_cleanup.sh
blmm/scripts/cluster_blmm_compare.sh
blmm/scripts/cluster_blmm_concat.sh
blmm/scripts/cluster_blmm_results.sh
blmm/scripts/cluster_blmm_setup.sh
blmm/scripts/parse_yaml.sh
blmm/src/PeLS.py
blmm/src/__init__.py
blmm/src/cvxMatrix2d.py
blmm/src/est2d.py
blmm/src/est3d.py
blmm/src/fileio.py
blmm/src/npMatrix2d.py
blmm/src/npMatrix3d.py
test/__init__.py
test/Unit/__init__.py
test/Unit/cvxMatrix2d_tests.py
test/Unit/est2d_tests.py
test/Unit/est3d_tests.py
test/Unit/genTestDat.py
test/Unit/npMatrix2d_tests.py
test/Unit/npMatrix3d_tests.py
pyblmm-0.1.1.dist-info/METADATA
pyblmm-0.1.1.dist-info/WHEEL
pyblmm-0.1.1.dist-info/entry_points.txt
pyblmm-0.1.1.dist-info/top_level.txt
pyblmm-0.1.1.dist-info/RECORD
